[
    {
        "Name": "RDGW Logon",
        "Log": "Microsoft-Windows-TerminalServices-Gateway",
        "EventId": 302,
        "Description": ""
    },
    {
        "Name": "RDGW Logoff",
        "Log": "Microsoft-Windows-TerminalServices-Gateway",
        "EventId": 303,
        "Description": ""
    },
    {
        "Name": "Software Installed",
        "Log": "Application",
        "EventId": 11707,
        "Description": ""
    },
    {
        "Name": "Software Uninstalled",
        "Log": "Application",
        "EventId": 11724,
        "Description": ""
    },
    {
        "Name": "Event Log Started",
        "Log": "System",
        "EventId": 6005,
        "Description": ""
    },
    {
        "Name": "Event Log Stopped",
        "Log": "System",
        "EventId": 6006,
        "Description": ""
    },
    {
        "Name": "User Account Created",
        "Log": "Security",
        "EventId": 4720,
        "Description": ""
    },
    {
        "Name": "User Account Deleted",
        "Log": "Security",
        "EventId": 4726,
        "Description": ""
    },
    {
        "Name": "RDP Session",
        "Log": "Microsoft-Windows-TerminalServices-LocalSessionManager",
        "EventId": 21,
        "Description": ""
    },
    {
        "Name": "BitLocker Encryption",
        "Log": "System",
        "EventId": 24667,
        "Description": ""
    },
    {
        "Name": "Task Scheduler Task Completed",
        "Log": "Microsoft-Windows-TaskScheduler",
        "EventId": 102,
        "Description": ""
    },
    {
        "Name": "Task Scheduler Action Completed",
        "Log": "Microsoft-Windows-TaskScheduler",
        "EventId": 201,
        "Description": ""
    },
    {
        "Name": "Task Scheduler Action Startd",
        "Log": "Microsoft-Windows-TaskScheduler",
        "EventId": 200,
        "Description": ""
    },
    {
        "Name": "Task Scheduler Created Task Process",
        "Log": "Microsoft-Windows-TaskScheduler",
        "EventId": 129,
        "Description": ""
    },
    {
        "Name": "Windows Defender Scan Started",
        "Log": "Microsoft-Windows-Windows Defender",
        "EventId": 1000,
        "Description": ""
    },
    {
        "Name": "Windows Defender Scan Completed",
        "Log": "Microsoft-Windows-Windows Defender",
        "EventId": 1001,
        "Description": ""
    },
    {
        "Name": "Windows Defender Malware Found",
        "Log": "Microsoft-Windows-Windows Defender",
        "EventId": 1006,
        "Description": "The antimalware engine found malware or other potentially unwanted software"
    },
    {
        "Name": "Windows Defender Peformed Action",
        "Log": "Microsoft-Windows-Windows Defender",
        "EventId": 1007,
        "Description": "The antimalware platform performed an action to protect your system from malware or other potentially unwanted software"
    },
    {
        "Name": "Windows Defender Malware Detected",
        "Log": "Microsoft-Windows-Windows Defender",
        "EventId": 1116,
        "Description": "The antimalware platform detected malware or other potentially unwanted software"
    },
    {
        "Name": "Windows Defender Peformed Action",
        "Log": "Microsoft-Windows-Windows Defender",
        "EventId": 1117,
        "Description": "The antimalware platform performed an action to protect your system from malware or other potentially unwanted software"
    },
    {
        "Name": "Windows Server Feature Added",
        "Log": "Microsoft-Windows-ServerManager-DeploymentProvider",
        "EventId": 204,
        "Description": ""
    },
    {
        "Name": "Windows Server Feature Removed",
        "Log": "Microsoft-Windows-ServerManager-DeploymentProvider",
        "EventId": 304,
        "Description": ""
    },
    {
        "Name": "Failed Logon Attempt",
        "Log": "Security",
        "EventId": 4625,
        "Description": ""
    },
    {
        "Name": "Restart or Shutdown",
        "Log": "System",
        "EventId": 1074,
        "Description": ""
    },
    {
        "Name": "Process Created",
        "Log": "Security",
        "EventId": 4688,
        "Description": ""
    },
    {
        "Name": "Process Exited",
        "Log": "Security",
        "EventId": 4689,
        "Description": ""
    }
]